{"uid":"2290ac5982fa1659","name":"VerifyPetCanBeAddedThroughId","fullName":"DotNetTestingFramework:DotNetTestingFramework.Tests.API_Tests.PetsTest.VerifyPetCanBeAddedThroughId()","historyId":"9c86945dce565d8bcaca5ab9c6dc20de","time":{"start":1703328465639,"stop":1703328466055,"duration":416},"description":"Verify a pet can be added\nVerify pet controller API\n","descriptionHtml":"<p>Verify a pet can be added<br />\nVerify pet controller API</p>\n","status":"passed","statusMessage":"VerifyPetCanBeAddedThroughId","flaky":false,"newFailed":false,"newBroken":false,"newPassed":false,"retriesCount":0,"retriesStatusChange":false,"beforeStages":[],"testStage":{"description":"Verify a pet can be added\nVerify pet controller API\n","status":"passed","statusMessage":"VerifyPetCanBeAddedThroughId","steps":[],"attachments":[{"uid":"b796263c3dd2c9ce","name":"Console Output","source":"b796263c3dd2c9ce.txt","type":"text/plain","size":155}],"parameters":[],"shouldDisplayMessage":true,"stepsCount":0,"attachmentsCount":1,"hasContent":true},"afterStages":[],"labels":[{"name":"thread","value":"ParallelWorker#1"},{"name":"host","value":"fv-az1258-535"},{"name":"language","value":"C#"},{"name":"framework","value":"NUnit 3"},{"name":"package","value":"DotNetTestingFramework.Tests.API_Tests"},{"name":"testMethod","value":"VerifyPetCanBeAddedThroughId"},{"name":"testClass","value":"PetsTest"},{"name":"tag","value":"@Pets"},{"name":"tag","value":"PetsTest"},{"name":"tag","value":"API"},{"name":"resultFormat","value":"allure2"}],"parameters":[],"links":[],"hidden":false,"retry":false,"extra":{"severity":"normal","retries":[],"categories":[],"tags":["PetsTest","API","@Pets"]},"source":"2290ac5982fa1659.json","parameterValues":[]}