{"28873635e56d24a74afac3d211e91d3c":{"statistic":{"failed":0,"broken":0,"skipped":0,"passed":1,"unknown":0,"total":1},"items":[{"uid":"24279d97138dd073","reportUrl":"https://MB1lal.github.io/DotNetTestingFramework/28//#testresult/24279d97138dd073","status":"passed","statusDetails":"Verify loading of newly created elements","time":{"start":1703328300111,"stop":1703328307952,"duration":7841}}]},"4557e902d9d0054b5f8624cdc2a2b22d":{"statistic":{"failed":0,"broken":0,"skipped":0,"passed":1,"unknown":0,"total":1},"items":[{"uid":"6305baae3be559dc","reportUrl":"https://MB1lal.github.io/DotNetTestingFramework/28//#testresult/6305baae3be559dc","status":"passed","statusDetails":"Verify loading of hidden elements","time":{"start":1703328276971,"stop":1703328300106,"duration":23135}}]},"69e642e244cdf62ffb1540205c7a274a":{"statistic":{"failed":0,"broken":0,"skipped":0,"passed":1,"unknown":0,"total":1},"items":[{"uid":"dd4b6b36e61f403c","reportUrl":"https://MB1lal.github.io/DotNetTestingFramework/28//#testresult/dd4b6b36e61f403c","status":"passed","statusDetails":"VerifyJSConfirm","time":{"start":1703328303749,"stop":1703328306269,"duration":2520}}]},"5a5bf388f6c7db7f57a515a97144f226":{"statistic":{"failed":0,"broken":0,"skipped":0,"passed":1,"unknown":0,"total":1},"items":[{"uid":"32feeecabf66934","reportUrl":"https://MB1lal.github.io/DotNetTestingFramework/28//#testresult/32feeecabf66934","status":"passed","statusDetails":"VerifyNotificationMessages","time":{"start":1703328304557,"stop":1703328307696,"duration":3139}}]},"8efc17caf7a64bfba49147f9e38b615a":{"statistic":{"failed":0,"broken":0,"skipped":0,"passed":1,"unknown":0,"total":1},"items":[{"uid":"654ed62d593fef96","reportUrl":"https://MB1lal.github.io/DotNetTestingFramework/28//#testresult/654ed62d593fef96","status":"passed","statusDetails":"OrderIsSuccesfullyPlaced","time":{"start":1703328269026,"stop":1703328272447,"duration":3421}}]},"f0b15fdd92f4d9fadeb7060adf39ea71":{"statistic":{"failed":0,"broken":0,"skipped":0,"passed":1,"unknown":0,"total":1},"items":[{"uid":"7e5399aab0ec347b","reportUrl":"https://MB1lal.github.io/DotNetTestingFramework/28//#testresult/7e5399aab0ec347b","status":"passed","statusDetails":"VerifyProfileTextOnHover","time":{"start":1703328297618,"stop":1703328300964,"duration":3346}}]},"d1028841ecf96b716ae5bc4aa6e07cd8":{"statistic":{"failed":0,"broken":0,"skipped":0,"passed":1,"unknown":0,"total":1},"items":[{"uid":"e35094ab494830d4","reportUrl":"https://MB1lal.github.io/DotNetTestingFramework/28//#testresult/e35094ab494830d4","status":"passed","statusDetails":"UserLogoutTest","time":{"start":1703328272656,"stop":1703328275520,"duration":2864}}]},"9c86945dce565d8bcaca5ab9c6dc20de":{"statistic":{"failed":0,"broken":0,"skipped":0,"passed":1,"unknown":0,"total":1},"items":[{"uid":"abc918c319928e3f","reportUrl":"https://MB1lal.github.io/DotNetTestingFramework/28//#testresult/abc918c319928e3f","status":"passed","statusDetails":"VerifyPetCanBeAddedThroughId","time":{"start":1703328272468,"stop":1703328272905,"duration":437}}]},"8181e18e40e174cd0065acba2347c7ec":{"statistic":{"failed":0,"broken":0,"skipped":0,"passed":1,"unknown":0,"total":1},"items":[{"uid":"1db2af23545ea84c","reportUrl":"https://MB1lal.github.io/DotNetTestingFramework/28//#testresult/1db2af23545ea84c","status":"passed","statusDetails":"VerifyCheckboxesUnchecking","time":{"start":1703328294696,"stop":1703328297366,"duration":2670}}]},"cf2e3339106e27f6cb536573e17d06ae":{"statistic":{"failed":0,"broken":0,"skipped":0,"passed":1,"unknown":0,"total":1},"items":[{"uid":"6a7df09f19ba8c51","reportUrl":"https://MB1lal.github.io/DotNetTestingFramework/28//#testresult/6a7df09f19ba8c51","status":"passed","statusDetails":"VerifyCheckboxesChecking","time":{"start":1703328273090,"stop":1703328294695,"duration":21605}}]},"5f08d65229adf9fa2b45c2e3c9715d2a":{"statistic":{"failed":0,"broken":0,"skipped":0,"passed":1,"unknown":0,"total":1},"items":[{"uid":"5e94e5827ce1ab69","reportUrl":"https://MB1lal.github.io/DotNetTestingFramework/28//#testresult/5e94e5827ce1ab69","status":"passed","statusDetails":"Verify dropdown option is correctly selected","time":{"start":1703328275521,"stop":1703328294758,"duration":19237}}]},"24b4f5439e4b398d2c5f31b0dcb48e54":{"statistic":{"failed":0,"broken":0,"skipped":0,"passed":1,"unknown":0,"total":1},"items":[{"uid":"a2d2a953f39fe1ad","reportUrl":"https://MB1lal.github.io/DotNetTestingFramework/28//#testresult/a2d2a953f39fe1ad","status":"passed","statusDetails":"VerifyNestedFrames","time":{"start":1703328301509,"stop":1703328304556,"duration":3047}}]},"8d4c90a83433ed9a16278b3e85d4e17d":{"statistic":{"failed":0,"broken":0,"skipped":0,"passed":1,"unknown":0,"total":1},"items":[{"uid":"14870547b7050919","reportUrl":"https://MB1lal.github.io/DotNetTestingFramework/28//#testresult/14870547b7050919","status":"passed","statusDetails":"VerifyJSALerts","time":{"start":1703328300973,"stop":1703328303749,"duration":2776}}]},"1e1887e918cceeff501a208f4f69e38a":{"statistic":{"failed":0,"broken":0,"skipped":0,"passed":1,"unknown":0,"total":1},"items":[{"uid":"43524d720c99841e","reportUrl":"https://MB1lal.github.io/DotNetTestingFramework/28//#testresult/43524d720c99841e","status":"passed","statusDetails":"VerifyPetsDetailsCanBeUpdated","time":{"start":1703328276118,"stop":1703328276970,"duration":852}}]},"08c238e1471eaf6fb0610167f7ec6f5f":{"statistic":{"failed":0,"broken":0,"skipped":0,"passed":1,"unknown":0,"total":1},"items":[{"uid":"aae6c76ee730d066","reportUrl":"https://MB1lal.github.io/DotNetTestingFramework/28//#testresult/aae6c76ee730d066","status":"passed","statusDetails":"Verify unsuccessful login","time":{"start":1703328295585,"stop":1703328298707,"duration":3122}}]},"b293437be9dd13152995dc596829c6fb":{"statistic":{"failed":0,"broken":0,"skipped":0,"passed":1,"unknown":0,"total":1},"items":[{"uid":"8e75a16d03782f17","reportUrl":"https://MB1lal.github.io/DotNetTestingFramework/28//#testresult/8e75a16d03782f17","status":"passed","statusDetails":"UserLoginTest","time":{"start":1703328269026,"stop":1703328272655,"duration":3629}}]},"2e00685d43982ead07b9fdf8340d68f5":{"statistic":{"failed":0,"broken":0,"skipped":0,"passed":1,"unknown":0,"total":1},"items":[{"uid":"dbc4817a68ee1635","reportUrl":"https://MB1lal.github.io/DotNetTestingFramework/28//#testresult/dbc4817a68ee1635","status":"passed","statusDetails":"VerifyJSPrompts","time":{"start":1703328306269,"stop":1703328308668,"duration":2399}}]},"2c2f4b80bf4d6b194f8a89a339a498be":{"statistic":{"failed":0,"broken":0,"skipped":0,"passed":1,"unknown":0,"total":1},"items":[{"uid":"c6301521dbf05e4d","reportUrl":"https://MB1lal.github.io/DotNetTestingFramework/28//#testresult/c6301521dbf05e4d","status":"passed","statusDetails":"VerifyFileUpload","time":{"start":1703328294762,"stop":1703328297617,"duration":2855}}]},"a16b5812be1e2a5d692edf3f87ebd00e":{"statistic":{"failed":0,"broken":0,"skipped":0,"passed":1,"unknown":0,"total":1},"items":[{"uid":"190b585da5f5b6d2","reportUrl":"https://MB1lal.github.io/DotNetTestingFramework/28//#testresult/190b585da5f5b6d2","status":"passed","statusDetails":"OrderIsSuccessfullyDeleted","time":{"start":1703328272468,"stop":1703328273086,"duration":618}}]},"26daf0e35d7fb78c2af6a35b1310f434":{"statistic":{"failed":0,"broken":0,"skipped":0,"passed":1,"unknown":0,"total":1},"items":[{"uid":"c4660e3583a18ab9","reportUrl":"https://MB1lal.github.io/DotNetTestingFramework/28//#testresult/c4660e3583a18ab9","status":"passed","statusDetails":"Verify successful login","time":{"start":1703328269026,"stop":1703328295585,"duration":26559}}]},"c807f9a47e2d215207681f4f3b6b2ab6":{"statistic":{"failed":0,"broken":0,"skipped":0,"passed":1,"unknown":0,"total":1},"items":[{"uid":"8d161e64e437b0ac","reportUrl":"https://MB1lal.github.io/DotNetTestingFramework/28//#testresult/8d161e64e437b0ac","status":"passed","statusDetails":"UserLogoutTest","time":{"start":1703328298708,"stop":1703328301946,"duration":3238}}]},"3963eae45a660a1776b2448b1066fbe2":{"statistic":{"failed":0,"broken":0,"skipped":0,"passed":1,"unknown":0,"total":1},"items":[{"uid":"22a37ef26400b0a1","reportUrl":"https://MB1lal.github.io/DotNetTestingFramework/28//#testresult/22a37ef26400b0a1","status":"passed","statusDetails":"VerifyiFrames","time":{"start":1703328297368,"stop":1703328301508,"duration":4140}}]},"6373e3ee8f88866755a85da0ee5531f9":{"statistic":{"failed":0,"broken":0,"skipped":0,"passed":1,"unknown":0,"total":1},"items":[{"uid":"3479f8c374d62aa8","reportUrl":"https://MB1lal.github.io/DotNetTestingFramework/28//#testresult/3479f8c374d62aa8","status":"passed","statusDetails":"VerifyPetCanBeDeleted","time":{"start":1703328272905,"stop":1703328276115,"duration":3210}}]},"50e0ad3005f85668f08c6a2763c68909":{"statistic":{"failed":0,"broken":0,"skipped":0,"passed":1,"unknown":0,"total":1},"items":[{"uid":"6ade124ca8eb1a8a","reportUrl":"https://MB1lal.github.io/DotNetTestingFramework/28//#testresult/6ade124ca8eb1a8a","status":"passed","statusDetails":"VerifyNewlyAddedPetThroughStatus","time":{"start":1703328269026,"stop":1703328272449,"duration":3423}}]},"d7ab5624581f7df7d0dcd76a666ad56a":{"statistic":{"failed":0,"broken":0,"skipped":0,"passed":1,"unknown":0,"total":1},"items":[{"uid":"5055f19665694350","reportUrl":"https://MB1lal.github.io/DotNetTestingFramework/28//#testresult/5055f19665694350","status":"passed","statusDetails":"VerifyMultipleTabsHandling","time":{"start":1703328301949,"stop":1703328304650,"duration":2701}}]}}